restack_google_gemini/__init__.py
restack_google_gemini/functions/__init__.py
restack_google_gemini/functions/chat/__init__.py
restack_google_gemini/functions/chat/get_history.py
restack_google_gemini/functions/chat/send_message.py
restack_google_gemini/functions/chat/start_chat.py
restack_google_gemini/functions/generate_content.py
restack_google_gemini/py.typed
restack_google_gemini/service.py
restack_google_gemini/task_queue.py
restack_google_gemini/utils/__init__.py
restack_google_gemini-0.0.26.dist-info/METADATA
restack_google_gemini-0.0.26.dist-info/WHEEL
restack_google_gemini-0.0.26.dist-info/RECORD
